letters/__init__.py
letters/ascii.py
letters/asciiart.py
letters/center.py
letters/colors.py
letters/fade.py
letters/style.py
letters/system.py
letters-2.0.1.dist-info/LICENSE
letters-2.0.1.dist-info/METADATA
letters-2.0.1.dist-info/WHEEL
letters-2.0.1.dist-info/top_level.txt
letters-2.0.1.dist-info/RECORD
