Metadata-Version: 2.1
Name: letters
Version: 2.0.1
Summary: A simple method to customize your programs to infinity!
Home-page: https://github.com/zeloww/letters
License: GPLv3+
Keywords: python,py,letter,letters,font,ascii,color,colors,gradient,gradients,fadetext
Platform: UNKNOWN
License-File: LICENSE
Requires-Dist: numpy
Requires-Dist: pillow
